clingolp/__init__.py
clingolp/app.py
clingolp/cplx.py
clingolp/lp_theory.py
clingolp/lps.py
clingo_lp-0.2.0.dist-info/LICENSE
clingo_lp-0.2.0.dist-info/METADATA
clingo_lp-0.2.0.dist-info/WHEEL
clingo_lp-0.2.0.dist-info/entry_points.txt
clingo_lp-0.2.0.dist-info/top_level.txt
clingo_lp-0.2.0.dist-info/RECORD
