Metadata-Version: 2.1
Name: clingo-lp
Version: 0.2.0
Summary: clingo[LP] extends the ASP solver clingo with linear constraints as dealt with in Linear Programming (LP).
Home-page: http://github.com/potassco/clingoLP/
Author: Sebastian Schellhorn
License: MIT
Platform: UNKNOWN
License-File: LICENSE
